setup.py
stripping/__init__.py
stripping/benchmark.py
stripping/cache.py
stripping/decorators.py
stripping/exceptions.py
stripping/executor.py
stripping/logging.py
stripping/singleton.py
stripping/storage.py
stripping/to_bytes.py
stripping.egg-info/PKG-INFO
stripping.egg-info/SOURCES.txt
stripping.egg-info/dependency_links.txt
stripping.egg-info/requires.txt
stripping.egg-info/top_level.txt
stripping/elemental/__init__.py
stripping/elemental/base.py
stripping/elemental/filters.py