Metadata-Version: 1.2
Name: stripping
Version: 0.2.6
Summary: An easy to use pipeline solution for AI/ML experiments
Home-page: https://github.com/exponential-ventures/stripping
Author: Adriano Marques, Nathan Martins, Thales Ribeiro
Author-email: adriano@xnv.io, nathan@xnv.io, thales@xnv.io
License: GNU LGPLv3
Platform: any
Classifier: License :: OSI Approved :: GNU General Public License v3 (GPLv3)
Classifier: Operating System :: OS Independent
Classifier: Programming Language :: Python
Classifier: Programming Language :: Python :: 3.7
Classifier: Programming Language :: Python :: Implementation :: CPython
Requires-Python: >=3.7.0
